CHANGELOG.md
airbornerf_data_validator/__init__.py
airbornerf_data_validator/constants.py
airbornerf_data_validator/core.py
airbornerf_data_validator/main.py
airbornerf_data_validator/rules.py
airbornerf_data_validator/utils.py
airbornerf_data_validator-1.1.2.dist-info/METADATA
airbornerf_data_validator-1.1.2.dist-info/WHEEL
airbornerf_data_validator-1.1.2.dist-info/entry_points.txt
airbornerf_data_validator-1.1.2.dist-info/RECORD
